jupyterlab_display_name/__init__.py
jupyterlab_display_name/py.typed
jupyterlab_display_name/templates/login.html
jupyterlab_display_name-0.2.1.data/data/etc/jupyter/jupyter_server_config.d/jupyterlab_display_name.json
jupyterlab_display_name-0.2.1.data/data/share/jupyter/labextensions/jupyterlab-display-name/package.json
jupyterlab_display_name-0.2.1.data/data/share/jupyter/labextensions/jupyterlab-display-name/static/509.535d8c73a4fcdba017ea.js
jupyterlab_display_name-0.2.1.data/data/share/jupyter/labextensions/jupyterlab-display-name/static/remoteEntry.02de88e05debcbf36904.js
jupyterlab_display_name-0.2.1.data/data/share/jupyter/labextensions/jupyterlab-display-name/static/style.js
jupyterlab_display_name-0.2.1.data/data/share/jupyter/labextensions/jupyterlab-display-name/static/third-party-licenses.json
jupyterlab_display_name-0.2.1.data/data/share/jupyter/labextensions/jupyterlab-display-name/install.json
jupyterlab_display_name-0.2.1.dist-info/METADATA
jupyterlab_display_name-0.2.1.dist-info/WHEEL
jupyterlab_display_name-0.2.1.dist-info/licenses/LICENSE
jupyterlab_display_name-0.2.1.dist-info/RECORD
