Metadata-Version: 2.3
Name: jupyterlab-display-name
Version: 0.2.1
Dynamic: Author
Dynamic: Author-email
Summary: JupyterLab server extension that adds a display name field to the login page.
Project-URL: Homepage, https://github.com/PainterQubits/jupyterlab-display-name
Project-URL: Repository, https://github.com/PainterQubits/jupyterlab-display-name
License: BSD 3-Clause License
License-File: LICENSE
Keywords: jupyter,jupyterlab,jupyterlab-extension
Classifier: Framework :: Jupyter
Classifier: Framework :: Jupyter :: JupyterLab
Classifier: Framework :: Jupyter :: JupyterLab :: 4
Classifier: Framework :: Jupyter :: JupyterLab :: Extensions
Classifier: Framework :: Jupyter :: JupyterLab :: Extensions :: Prebuilt
Classifier: License :: OSI Approved :: BSD License
Classifier: Programming Language :: Python
Classifier: Programming Language :: Python :: 3
Classifier: Programming Language :: Python :: 3.9
Classifier: Programming Language :: Python :: 3.10
Classifier: Programming Language :: Python :: 3.11
Classifier: Programming Language :: Python :: 3.12
Requires-Python: >=3.9
Requires-Dist: jupyter-server<3,>=2.14.2
Requires-Dist: tornado<7,>=6.4.1
